odoo/addons/ssi_service_quotation_project/README.rst
odoo/addons/ssi_service_quotation_project/__init__.py
odoo/addons/ssi_service_quotation_project/__manifest__.py
odoo/addons/ssi_service_quotation_project/models/__init__.py
odoo/addons/ssi_service_quotation_project/models/service_quotation.py
odoo/addons/ssi_service_quotation_project/static/description/icon.png
odoo14_addon_ssi_service_quotation_project-14.0.1.0.2.dev1.dist-info/METADATA
odoo14_addon_ssi_service_quotation_project-14.0.1.0.2.dev1.dist-info/WHEEL
odoo14_addon_ssi_service_quotation_project-14.0.1.0.2.dev1.dist-info/top_level.txt
odoo14_addon_ssi_service_quotation_project-14.0.1.0.2.dev1.dist-info/RECORD
